{"transcript":"ﾉ嬾 ﾋ埶pikﾉ决 i ﾋ𡌛ﾉｪstﾉ冢","exists":true,"definitions":["En handling eller hendelse som bidrar til ﾃ･ ﾃｸdelegge eller avslutte noe.","Noe som fremskynder slutten pﾃ･ noe."],"examples":["Nedleggelsen av fabrikken var en spiker i kisten for lokalsamfunnet.","Den dﾃ･rlige anmeldelsen var en spiker i kisten for teaterstykket.","Hﾃｸye renter var en spiker i kisten for mange smﾃ･bedrifter."],"lemma":"en spiker i kisten","lemmaPos":"idiom","synonyms":["dﾃｸdsstﾃｸtet","nﾃ･destﾃｸtet"],"number":"singular","source":"en spiker i kisten"}