{"transcript":"…î Υàk…îbl…ô Υàs…ëm…ôn","exists":true,"definitions":["ΟΞ fΟΗre to eller flere deler sammen","ΟΞ opprette en forbindelse mellom enheter","ΟΞ knytte sammen teknisk utstyr eller ideer"],"examples":["Vi mΟΞ koble sammen ledningene.","Han prΟΗver ΟΞ koble sammen maskinene.","Kan du koble sammen disse to punktene?"],"lemma":"ΟΞ koble sammen","lemmaPos":"verb","synonyms":["forbinde","sammenfΟΗye","knytte","kople"],"number":"singular","pastTenses":"koblet sammen, har koblet sammen","tense":"infinitive","source":"ΟΞ koble sammen"}