{"transcript":"ˈkruːnə","exists":true,"definitions":["Myntenhet i Norge og Danmark, tilsvarende 100 øre.","En kongelig eller keiserlig hodebekledning, ofte symbol på makt og verdighet.","Den øverste delen av et tre, bestående av grener og løvverk.","Den synlige delen av en tann, som stikker opp over tannkjøttet."],"examples":["En krone er verdt hundre øre.","Kongen bar en tung krone.","Treet hadde en stor krone.","Tannlegen satte på en ny krone."],"lemma":"krone","lemmaPos":"noun","synonyms":["mynt","diadem","topp","tannkrone"],"number":"singular","gender":"feminine","source":"krone"}