{"transcript":"ɡʉːd","exists":true,"definitions":["Den øverste skapende og styrende makt i universet, spesielt i monoteistiske religioner.","Et vesen eller en ånd som blir tilbedt og antatt å ha overnaturlige krefter eller kontroll over en del av verden eller livet."],"examples":["Gud skapte verden på seks dager.","Be til Gud om hjelp.","Gud velsigne deg."],"lemma":"Gud","lemmaPos":"proper noun","synonyms":["Herren","Skaperen","Vårherre"],"number":"singular","pluralForm":"guder","gender":"masculine","source":"Gud"}