{"transcript":"ˈnɪ̂sːə","exists":true,"definitions":["Vesen i nordisk folketro, ofte fremstilt som en liten mann med rød lue, som bor på gårder og hjelper til, men som også kan være rampete.","Liten figur, ofte av keramikk eller plast, som forestiller en nisse, brukt som dekorasjon, særlig til jul.","Kallenavn på julenissen."],"examples":["Nissen på låven.","En hel flokk med nisser.","Barna trodde på nissen."],"lemma":"nisse","lemmaPos":"noun","synonyms":["fjøsnisse","gårdnisse","julenisse"],"number":"singular","pluralForm":"nisser","gender":"masculine","source":"nisse"}