{"transcript":"ňą Čn…ôrňĆdriňźv…ôls…ô","exists":true,"definitions":["En underdrivelse er en retorisk figur der man bevisst fremstiller noe som mindre viktig, mindre alvorlig eller mindre betydningsfullt enn det faktisk er.","Uttrykk som bevisst nedtoner betydningen av noe."],"examples":["√Ö si at det var en utfordring, var en underdrivelse.","Det er en grov underdrivelse √• kalle det en liten feil."],"lemma":"underdrivelse","lemmaPos":"noun","synonyms":["nedtoning","understatement"],"number":"singular","pluralForm":"underdrivelser","gender":"feminine","source":"underdrivelse"}