{"transcript":"ﾋ埇ﾉ創ﾋ尽ﾉ鼠dﾉ决","exists":true,"definitions":["Tidsrommet en mann lever, regnet som en gjennomsnittlig levetid for et menneske.","En lang tidsperiode, ofte rundt 70-100 ﾃ･r, brukt for ﾃ･ beskrive en generasjon eller en epoke."],"examples":["Det er en mannsalder siden sist vi mﾃｸttes.","Bygningen har stﾃ･tt i en mannsalder.","En mannsalder med erfaring."],"lemma":"mannsalder","lemmaPos":"noun","synonyms":["generasjon","levetid","lang tid"],"number":"singular","pluralForm":"mannsaldre","gender":"masculine","source":"mannsalder"}