{"transcript":"ɛn ˈivæʂɛt:əlsə","exists":true,"definitions":["Handling eller prosess med å sette noe i verk; implementering.","Gjennomføring av en plan, beslutning eller lov."],"examples":["Iverksettelse av prosjektet er planlagt til neste måned.","Regjeringen jobber med iverksettelse av nye miljøtiltak.","En rask iverksettelse var nødvendig."],"lemma":"iverksettelse","lemmaPos":"noun","synonyms":["implementering","gjennomføring","utførelse"],"number":"singular","pluralForm":"iverksettelser","gender":"masculine","source":"iverksettelse"}