{"transcript":"틛툶톩p톛틟b톛틟h톔n:l톩콂","exists":true,"definitions":["En kosmetisk prosedyre for 친 forbedre utseendet til 칮yevipper.","Behandling som involverer farging, l칮ft eller forlengelse av 칮yevipper."],"examples":["Hun bestilte en vippebehandling.","Resultatet av vippebehandlingen var fantastisk.","Hvor mye koster en vippebehandling?"],"lemma":"vippebehandling","lemmaPos":"noun","synonyms":["vippel칮ft","vippeforlengelse","vippefarging"],"number":"singular","pluralForm":"vippebehandlinger","gender":"feminine","source":"vippebehandling"}